setup.py
JIM_server.egg-info/PKG-INFO
JIM_server.egg-info/SOURCES.txt
JIM_server.egg-info/dependency_links.txt
JIM_server.egg-info/requires.txt
JIM_server.egg-info/top_level.txt
server/__init__.py
server/server.py
server/server_gui.py
server/common/__init__.py
server/common/setting.py
server/common/utils.py
server/decorators/__init__.py
server/decorators/decorators.py
server/descriptors/__init__.py
server/descriptors/descriptors.py
server/log/__init__.py
server/log/client/__init__.py
server/log/client/client_log.py
server/log/server/__init__.py
server/log/server/server_log.py
server/log/utils/__init__.py
server/log/utils/utils_log.py
server/metaclasses/__init__.py
server/metaclasses/metaclasses.py
server/server/__init__.py
server/server/server.py
server/server/server_db.py
server/server/server_gui.py
server/tests/__init__.py
server/tests/protocols_test.py
server/tests/server_test.py