Metadata-Version: 1.0
Name: JIM-server
Version: 0.0.1
Summary: messegers server
Home-page: UNKNOWN
Author: Firdos Aliev
Author-email: firdos1234567891@gmail.com
License: UNKNOWN
Platform: UNKNOWN
